witchery/__about__.py
witchery/__init__.py
witchery/py.typed
witchery-0.3.1.dist-info/METADATA
witchery-0.3.1.dist-info/WHEEL
witchery-0.3.1.dist-info/licenses/LICENSE.txt
witchery-0.3.1.dist-info/RECORD
