Metadata-Version: 2.4
Name: witchery
Version: 0.3.1
Summary: Witchery is a powerful Python library that offers various functionalities for code analysis and modification.
Project-URL: Documentation, https://github.com/robinvandernoord/witchery#readme
Project-URL: Issues, https://github.com/robinvandernoord/witchery/issues
Project-URL: Source, https://github.com/robinvandernoord/witchery
Author-email: Robin van der Noord <robinvandernoord@gmail.com>
License-Expression: MIT
License-File: LICENSE.txt
Keywords: databases,pydal,sql
Classifier: Development Status :: 4 - Beta
Classifier: Programming Language :: Python
Classifier: Programming Language :: Python :: 3.10
Classifier: Programming Language :: Python :: 3.11
Classifier: Programming Language :: Python :: 3.12
Classifier: Programming Language :: Python :: 3.13
Classifier: Programming Language :: Python :: 3.14
Classifier: Programming Language :: Python :: Implementation :: CPython
Classifier: Programming Language :: Python :: Implementation :: PyPy
Requires-Python: >=3.10
Provides-Extra: dev
Requires-Dist: hatch; extra == 'dev'
Requires-Dist: pydal; extra == 'dev'
Requires-Dist: python-semantic-release<8; extra == 'dev'
Requires-Dist: su6[all]; extra == 'dev'
